README.md
setup.py
mummer_idotplot/__init__.py
mummer_idotplot/main.py
mummer_idotplot/mummer_interactive_dotplot.py
mummer_idotplot.egg-info/PKG-INFO
mummer_idotplot.egg-info/SOURCES.txt
mummer_idotplot.egg-info/dependency_links.txt
mummer_idotplot.egg-info/entry_points.txt
mummer_idotplot.egg-info/requires.txt
mummer_idotplot.egg-info/top_level.txt