Metadata-Version: 2.1
Name: mummer-idotplot
Version: 0.1.3
Summary: Generate interactive dotplot from MUMmer4 output using plotly
Home-page: https://github.com/ryought/mummer-idotplot
Author: ryought
Author-email: ryonakabayashi@gmail.com
License: MIT
Platform: UNKNOWN
